QuantumRandomWalks/QRW.py
QuantumRandomWalks/__init__.py
QuantumRandomWalks/post_processing.py
quantumrandomwalks-0.0.5.dist-info/licenses/LICENSE
quantumrandomwalks-0.0.5.dist-info/METADATA
quantumrandomwalks-0.0.5.dist-info/WHEEL
quantumrandomwalks-0.0.5.dist-info/top_level.txt
quantumrandomwalks-0.0.5.dist-info/RECORD
