Metadata-Version: 2.4
Name: QuantumRandomWalks
Version: 0.0.5
Summary: This package was made to perform continous time quantum random walks on domain-specific networks
Author: Jose Hernandez
Author-email: jose.hndz.prz@gmail.com
Classifier: Programming Language :: Python :: 3
Classifier: License :: OSI Approved :: MIT License
Classifier: Operating System :: OS Independent
Requires-Python: >=3.6
License-File: LICENSE
Requires-Dist: numpy
Requires-Dist: pandas
Requires-Dist: qiskit
Requires-Dist: qiksit-aer
Requires-Dist: scipy
Dynamic: license-file
